numpysocket/__init__.py
numpysocket/numpysocket.py
numpysocket-2.0.2.dist-info/METADATA
numpysocket-2.0.2.dist-info/WHEEL
numpysocket-2.0.2.dist-info/licenses/LICENSE
numpysocket-2.0.2.dist-info/RECORD
