Metadata-Version: 2.4
Name: numpysocket
Version: 2.0.2
Summary: Socket.Socket Subclass for Sending Numpy Arrays
Project-URL: Homepage, https://github.com/sabjorn/numpysocket
Author-email: "Steven A. Bjornson" <info@sabjorn.net>
License: MIT License
License-File: LICENSE
Classifier: License :: OSI Approved :: MIT License
Classifier: Operating System :: OS Independent
Classifier: Programming Language :: Python :: 3
Requires-Python: >=3.9
Requires-Dist: numpy>=2.0.0
